{
    "nodes": [
        {
            "id": "backend_zverts_backend",
            "label": "ZverTs Backend Specification",
            "file_type": "document",
            "source_file": "BACKEND.md",
            "source_location": "1-874",
            "source_url": null,
            "captured_at": null,
            "author": null,
            "contributor": null
        },
        {
            "id": "backend_modular_monolith",
            "label": "Modular Monolith Architecture",
            "file_type": "rationale",
            "source_file": "BACKEND.md",
            "source_location": "11-18",
            "source_url": null,
            "captured_at": null,
            "author": null,
            "contributor": null
        },
        {
            "id": "backend_zverts_api",
            "label": "zverts-api HTTP Server",
            "file_type": "concept",
            "source_file": "BACKEND.md",
            "source_location": "13",
            "source_url": null,
            "captured_at": null,
            "author": null,
            "contributor": null
        },
        {
            "id": "backend_zverts_worker",
            "label": "zverts-worker Background Process",
            "file_type": "concept",
            "source_file": "BACKEND.md",
            "source_location": "14",
            "source_url": null,
            "captured_at": null,
            "author": null,
            "contributor": null
        },
        {
            "id": "backend_zverts_migrate",
            "label": "zverts-migrate One-shot Job",
            "file_type": "concept",
            "source_file": "BACKEND.md",
            "source_location": "19",
            "source_url": null,
            "captured_at": null,
            "author": null,
            "contributor": null
        },
        {
            "id": "backend_auth_module",
            "label": "Auth Module",
            "file_type": "concept",
            "source_file": "BACKEND.md",
            "source_location": "26",
            "source_url": null,
            "captured_at": null,
            "author": null,
            "contributor": null
        },
        {
            "id": "backend_users_module",
            "label": "Users Module",
            "file_type": "concept",
            "source_file": "BACKEND.md",
            "source_location": "27",
            "source_url": null,
            "captured_at": null,
            "author": null,
            "contributor": null
        },
        {
            "id": "backend_courses_module",
            "label": "Courses Module",
            "file_type": "concept",
            "source_file": "BACKEND.md",
            "source_location": "28",
            "source_url": null,
            "captured_at": null,
            "author": null,
            "contributor": null
        },
        {
            "id": "backend_import_module",
            "label": "Import Module",
            "file_type": "concept",
            "source_file": "BACKEND.md",
            "source_location": "29",
            "source_url": null,
            "captured_at": null,
            "author": null,
            "contributor": null
        },
        {
            "id": "backend_learn_module",
            "label": "Learn Module",
            "file_type": "concept",
            "source_file": "BACKEND.md",
            "source_location": "30",
            "source_url": null,
            "captured_at": null,
            "author": null,
            "contributor": null
        },
        {
            "id": "backend_quiz_module",
            "label": "Quiz Module",
            "file_type": "concept",
            "source_file": "BACKEND.md",
            "source_location": "31",
            "source_url": null,
            "captured_at": null,
            "author": null,
            "contributor": null
        },
        {
            "id": "backend_gamification_module",
            "label": "Gamification Module",
            "file_type": "concept",
            "source_file": "BACKEND.md",
            "source_location": "32",
            "source_url": null,
            "captured_at": null,
            "author": null,
            "contributor": null
        },
        {
            "id": "backend_certificates_module",
            "label": "Certificates Module",
            "file_type": "concept",
            "source_file": "BACKEND.md",
            "source_location": "33",
            "source_url": null,
            "captured_at": null,
            "author": null,
            "contributor": null
        },
        {
            "id": "backend_tutor_module",
            "label": "Tutor Module (Stateless SSE Proxy)",
            "file_type": "concept",
            "source_file": "BACKEND.md",
            "source_location": "34",
            "source_url": null,
            "captured_at": null,
            "author": null,
            "contributor": null
        },
        {
            "id": "backend_notifications_module",
            "label": "Notifications Module",
            "file_type": "concept",
            "source_file": "BACKEND.md",
            "source_location": "35",
            "source_url": null,
            "captured_at": null,
            "author": null,
            "contributor": null
        },
        {
            "id": "backend_admin_module",
            "label": "Admin Module",
            "file_type": "concept",
            "source_file": "BACKEND.md",
            "source_location": "36",
            "source_url": null,
            "captured_at": null,
            "author": null,
            "contributor": null
        },
        {
            "id": "backend_storage_module",
            "label": "Storage Module",
            "file_type": "concept",
            "source_file": "BACKEND.md",
            "source_location": "37",
            "source_url": null,
            "captured_at": null,
            "author": null,
            "contributor": null
        },
        {
            "id": "backend_platform_module",
            "label": "Platform Module (Cross-cutting)",
            "file_type": "concept",
            "source_file": "BACKEND.md",
            "source_location": "38",
            "source_url": null,
            "captured_at": null,
            "author": null,
            "contributor": null
        },
        {
            "id": "backend_outbox_pattern",
            "label": "Outbox Pattern for Cross-module Events",
            "file_type": "rationale",
            "source_file": "BACKEND.md",
            "source_location": "43",
            "source_url": null,
            "captured_at": null,
            "author": null,
            "contributor": null
        },
        {
            "id": "backend_sse_hub",
            "label": "SSE Hub for Realtime Fan-out",
            "file_type": "concept",
            "source_file": "BACKEND.md",
            "source_location": "44",
            "source_url": null,
            "captured_at": null,
            "author": null,
            "contributor": null
        },
        {
            "id": "backend_profiles_table",
            "label": "profiles DB Table",
            "file_type": "concept",
            "source_file": "BACKEND.md",
            "source_location": "70-96",
            "source_url": null,
            "captured_at": null,
            "author": null,
            "contributor": null
        },
        {
            "id": "backend_user_roles_table",
            "label": "user_roles DB Table",
            "file_type": "concept",
            "source_file": "BACKEND.md",
            "source_location": "98-109",
            "source_url": null,
            "captured_at": null,
            "author": null,
            "contributor": null
        },
        {
            "id": "backend_courses_table",
            "label": "courses DB Table",
            "file_type": "concept",
            "source_file": "BACKEND.md",
            "source_location": "111-133",
            "source_url": null,
            "captured_at": null,
            "author": null,
            "contributor": null
        },
        {
            "id": "backend_modules_table",
            "label": "modules DB Table",
            "file_type": "concept",
            "source_file": "BACKEND.md",
            "source_location": "134-149",
            "source_url": null,
            "captured_at": null,
            "author": null,
            "contributor": null
        },
        {
            "id": "backend_module_progress_table",
            "label": "module_progress DB Table",
            "file_type": "concept",
            "source_file": "BACKEND.md",
            "source_location": "150-167",
            "source_url": null,
            "captured_at": null,
            "author": null,
            "contributor": null
        },
        {
            "id": "backend_notes_table",
            "label": "notes DB Table",
            "file_type": "concept",
            "source_file": "BACKEND.md",
            "source_location": "169-182",
            "source_url": null,
            "captured_at": null,
            "author": null,
            "contributor": null
        },
        {
            "id": "backend_mcq_questions_table",
            "label": "mcq_questions DB Table",
            "file_type": "concept",
            "source_file": "BACKEND.md",
            "source_location": "184-199",
            "source_url": null,
            "captured_at": null,
            "author": null,
            "contributor": null
        },
        {
            "id": "backend_mcq_attempts_table",
            "label": "mcq_attempts DB Table",
            "file_type": "concept",
            "source_file": "BACKEND.md",
            "source_location": "200-214",
            "source_url": null,
            "captured_at": null,
            "author": null,
            "contributor": null
        },
        {
            "id": "backend_daily_challenges_table",
            "label": "daily_challenges DB Table",
            "file_type": "concept",
            "source_file": "BACKEND.md",
            "source_location": "216-230",
            "source_url": null,
            "captured_at": null,
            "author": null,
            "contributor": null
        },
        {
            "id": "backend_attendance_table",
            "label": "attendance DB Table",
            "file_type": "concept",
            "source_file": "BACKEND.md",
            "source_location": "232-242",
            "source_url": null,
            "captured_at": null,
            "author": null,
            "contributor": null
        },
        {
            "id": "backend_achievements_table",
            "label": "achievements DB Table",
            "file_type": "concept",
            "source_file": "BACKEND.md",
            "source_location": "244-255",
            "source_url": null,
            "captured_at": null,
            "author": null,
            "contributor": null
        },
        {
            "id": "backend_certificates_table",
            "label": "certificates DB Table",
            "file_type": "concept",
            "source_file": "BACKEND.md",
            "source_location": "257-270",
            "source_url": null,
            "captured_at": null,
            "author": null,
            "contributor": null
        },
        {
            "id": "backend_email_logs_table",
            "label": "email_logs DB Table",
            "file_type": "concept",
            "source_file": "BACKEND.md",
            "source_location": "272-285",
            "source_url": null,
            "captured_at": null,
            "author": null,
            "contributor": null
        },
        {
            "id": "backend_outbox_events_table",
            "label": "outbox_events DB Table",
            "file_type": "concept",
            "source_file": "BACKEND.md",
            "source_location": "287-300",
            "source_url": null,
            "captured_at": null,
            "author": null,
            "contributor": null
        },
        {
            "id": "backend_idempotency_keys_table",
            "label": "idempotency_keys DB Table",
            "file_type": "concept",
            "source_file": "BACKEND.md",
            "source_location": "302-313",
            "source_url": null,
            "captured_at": null,
            "author": null,
            "contributor": null
        },
        {
            "id": "backend_riverqueue",
            "label": "River Queue (Postgres-backed Job Queue)",
            "file_type": "concept",
            "source_file": "BACKEND.md",
            "source_location": "561",
            "source_url": null,
            "captured_at": null,
            "author": null,
            "contributor": null
        },
        {
            "id": "backend_jwt_rs256",
            "label": "JWT RS256 Session Model",
            "file_type": "concept",
            "source_file": "BACKEND.md",
            "source_location": "494-498",
            "source_url": null,
            "captured_at": null,
            "author": null,
            "contributor": null
        },
        {
            "id": "backend_redis_strategy",
            "label": "Redis Cache and Rate Limit Strategy",
            "file_type": "concept",
            "source_file": "BACKEND.md",
            "source_location": "595-637",
            "source_url": null,
            "captured_at": null,
            "author": null,
            "contributor": null
        },
        {
            "id": "backend_authservice",
            "label": "AuthService",
            "file_type": "concept",
            "source_file": "BACKEND.md",
            "source_location": "537",
            "source_url": null,
            "captured_at": null,
            "author": null,
            "contributor": null
        },
        {
            "id": "backend_userservice",
            "label": "UserService",
            "file_type": "concept",
            "source_file": "BACKEND.md",
            "source_location": "538",
            "source_url": null,
            "captured_at": null,
            "author": null,
            "contributor": null
        },
        {
            "id": "backend_courseservice",
            "label": "CourseService",
            "file_type": "concept",
            "source_file": "BACKEND.md",
            "source_location": "539",
            "source_url": null,
            "captured_at": null,
            "author": null,
            "contributor": null
        },
        {
            "id": "backend_importservice",
            "label": "ImportService",
            "file_type": "concept",
            "source_file": "BACKEND.md",
            "source_location": "540",
            "source_url": null,
            "captured_at": null,
            "author": null,
            "contributor": null
        },
        {
            "id": "backend_progressservice",
            "label": "ProgressService",
            "file_type": "concept",
            "source_file": "BACKEND.md",
            "source_location": "542",
            "source_url": null,
            "captured_at": null,
            "author": null,
            "contributor": null
        },
        {
            "id": "backend_quizservice",
            "label": "QuizService",
            "file_type": "concept",
            "source_file": "BACKEND.md",
            "source_location": "544",
            "source_url": null,
            "captured_at": null,
            "author": null,
            "contributor": null
        },
        {
            "id": "backend_gamificationservice",
            "label": "GamificationService",
            "file_type": "concept",
            "source_file": "BACKEND.md",
            "source_location": "546",
            "source_url": null,
            "captured_at": null,
            "author": null,
            "contributor": null
        },
        {
            "id": "backend_certificateservice",
            "label": "CertificateService",
            "file_type": "concept",
            "source_file": "BACKEND.md",
            "source_location": "547",
            "source_url": null,
            "captured_at": null,
            "author": null,
            "contributor": null
        },
        {
            "id": "backend_tutorservice",
            "label": "TutorService (SSE Proxy)",
            "file_type": "concept",
            "source_file": "BACKEND.md",
            "source_location": "548",
            "source_url": null,
            "captured_at": null,
            "author": null,
            "contributor": null
        },
        {
            "id": "backend_notificationservice",
            "label": "NotificationService",
            "file_type": "concept",
            "source_file": "BACKEND.md",
            "source_location": "549",
            "source_url": null,
            "captured_at": null,
            "author": null,
            "contributor": null
        },
        {
            "id": "backend_adminservice",
            "label": "AdminService",
            "file_type": "concept",
            "source_file": "BACKEND.md",
            "source_location": "550",
            "source_url": null,
            "captured_at": null,
            "author": null,
            "contributor": null
        },
        {
            "id": "backend_ratelimitservice",
            "label": "RateLimitService (Token Bucket)",
            "file_type": "concept",
            "source_file": "BACKEND.md",
            "source_location": "554",
            "source_url": null,
            "captured_at": null,
            "author": null,
            "contributor": null
        }
    ],
    "edges": [
        {
            "source": "backend_zverts_backend",
            "target": "backend_modular_monolith",
            "relation": "references",
            "confidence": "EXTRACTED",
            "confidence_score": 1.0,
            "source_file": "BACKEND.md",
            "source_location": "11",
            "weight": 1.0
        },
        {
            "source": "backend_modular_monolith",
            "target": "backend_zverts_api",
            "relation": "conceptually_related_to",
            "confidence": "EXTRACTED",
            "confidence_score": 1.0,
            "source_file": "BACKEND.md",
            "source_location": "13",
            "weight": 1.0
        },
        {
            "source": "backend_modular_monolith",
            "target": "backend_zverts_worker",
            "relation": "conceptually_related_to",
            "confidence": "EXTRACTED",
            "confidence_score": 1.0,
            "source_file": "BACKEND.md",
            "source_location": "14",
            "weight": 1.0
        },
        {
            "source": "backend_modular_monolith",
            "target": "backend_zverts_migrate",
            "relation": "conceptually_related_to",
            "confidence": "EXTRACTED",
            "confidence_score": 1.0,
            "source_file": "BACKEND.md",
            "source_location": "19",
            "weight": 1.0
        },
        {
            "source": "backend_zverts_api",
            "target": "backend_auth_module",
            "relation": "conceptually_related_to",
            "confidence": "EXTRACTED",
            "confidence_score": 1.0,
            "source_file": "BACKEND.md",
            "source_location": "22",
            "weight": 1.0
        },
        {
            "source": "backend_zverts_api",
            "target": "backend_users_module",
            "relation": "conceptually_related_to",
            "confidence": "EXTRACTED",
            "confidence_score": 1.0,
            "source_file": "BACKEND.md",
            "source_location": "22",
            "weight": 1.0
        },
        {
            "source": "backend_zverts_api",
            "target": "backend_courses_module",
            "relation": "conceptually_related_to",
            "confidence": "EXTRACTED",
            "confidence_score": 1.0,
            "source_file": "BACKEND.md",
            "source_location": "22",
            "weight": 1.0
        },
        {
            "source": "backend_zverts_api",
            "target": "backend_import_module",
            "relation": "conceptually_related_to",
            "confidence": "EXTRACTED",
            "confidence_score": 1.0,
            "source_file": "BACKEND.md",
            "source_location": "22",
            "weight": 1.0
        },
        {
            "source": "backend_zverts_api",
            "target": "backend_learn_module",
            "relation": "conceptually_related_to",
            "confidence": "EXTRACTED",
            "confidence_score": 1.0,
            "source_file": "BACKEND.md",
            "source_location": "22",
            "weight": 1.0
        },
        {
            "source": "backend_zverts_api",
            "target": "backend_quiz_module",
            "relation": "conceptually_related_to",
            "confidence": "EXTRACTED",
            "confidence_score": 1.0,
            "source_file": "BACKEND.md",
            "source_location": "22",
            "weight": 1.0
        },
        {
            "source": "backend_zverts_api",
            "target": "backend_gamification_module",
            "relation": "conceptually_related_to",
            "confidence": "EXTRACTED",
            "confidence_score": 1.0,
            "source_file": "BACKEND.md",
            "source_location": "22",
            "weight": 1.0
        },
        {
            "source": "backend_zverts_api",
            "target": "backend_certificates_module",
            "relation": "conceptually_related_to",
            "confidence": "EXTRACTED",
            "confidence_score": 1.0,
            "source_file": "BACKEND.md",
            "source_location": "22",
            "weight": 1.0
        },
        {
            "source": "backend_zverts_api",
            "target": "backend_tutor_module",
            "relation": "conceptually_related_to",
            "confidence": "EXTRACTED",
            "confidence_score": 1.0,
            "source_file": "BACKEND.md",
            "source_location": "22",
            "weight": 1.0
        },
        {
            "source": "backend_zverts_api",
            "target": "backend_notifications_module",
            "relation": "conceptually_related_to",
            "confidence": "EXTRACTED",
            "confidence_score": 1.0,
            "source_file": "BACKEND.md",
            "source_location": "22",
            "weight": 1.0
        },
        {
            "source": "backend_zverts_api",
            "target": "backend_admin_module",
            "relation": "conceptually_related_to",
            "confidence": "EXTRACTED",
            "confidence_score": 1.0,
            "source_file": "BACKEND.md",
            "source_location": "22",
            "weight": 1.0
        },
        {
            "source": "backend_zverts_api",
            "target": "backend_storage_module",
            "relation": "conceptually_related_to",
            "confidence": "EXTRACTED",
            "confidence_score": 1.0,
            "source_file": "BACKEND.md",
            "source_location": "22",
            "weight": 1.0
        },
        {
            "source": "backend_zverts_api",
            "target": "backend_platform_module",
            "relation": "conceptually_related_to",
            "confidence": "EXTRACTED",
            "confidence_score": 1.0,
            "source_file": "BACKEND.md",
            "source_location": "22",
            "weight": 1.0
        },
        {
            "source": "backend_zverts_api",
            "target": "backend_riverqueue",
            "relation": "conceptually_related_to",
            "confidence": "EXTRACTED",
            "confidence_score": 1.0,
            "source_file": "BACKEND.md",
            "source_location": "43",
            "weight": 1.0
        },
        {
            "source": "backend_zverts_worker",
            "target": "backend_riverqueue",
            "relation": "conceptually_related_to",
            "confidence": "EXTRACTED",
            "confidence_score": 1.0,
            "source_file": "BACKEND.md",
            "source_location": "14",
            "weight": 1.0
        },
        {
            "source": "backend_zverts_api",
            "target": "backend_sse_hub",
            "relation": "conceptually_related_to",
            "confidence": "EXTRACTED",
            "confidence_score": 1.0,
            "source_file": "BACKEND.md",
            "source_location": "44",
            "weight": 1.0
        },
        {
            "source": "backend_outbox_pattern",
            "target": "backend_outbox_events_table",
            "relation": "references",
            "confidence": "EXTRACTED",
            "confidence_score": 1.0,
            "source_file": "BACKEND.md",
            "source_location": "287",
            "weight": 1.0
        },
        {
            "source": "backend_auth_module",
            "target": "backend_user_roles_table",
            "relation": "shares_data_with",
            "confidence": "EXTRACTED",
            "confidence_score": 1.0,
            "source_file": "BACKEND.md",
            "source_location": "26",
            "weight": 1.0
        },
        {
            "source": "backend_users_module",
            "target": "backend_profiles_table",
            "relation": "shares_data_with",
            "confidence": "EXTRACTED",
            "confidence_score": 1.0,
            "source_file": "BACKEND.md",
            "source_location": "27",
            "weight": 1.0
        },
        {
            "source": "backend_courses_module",
            "target": "backend_courses_table",
            "relation": "shares_data_with",
            "confidence": "EXTRACTED",
            "confidence_score": 1.0,
            "source_file": "BACKEND.md",
            "source_location": "28",
            "weight": 1.0
        },
        {
            "source": "backend_courses_module",
            "target": "backend_modules_table",
            "relation": "shares_data_with",
            "confidence": "EXTRACTED",
            "confidence_score": 1.0,
            "source_file": "BACKEND.md",
            "source_location": "28",
            "weight": 1.0
        },
        {
            "source": "backend_learn_module",
            "target": "backend_module_progress_table",
            "relation": "shares_data_with",
            "confidence": "EXTRACTED",
            "confidence_score": 1.0,
            "source_file": "BACKEND.md",
            "source_location": "30",
            "weight": 1.0
        },
        {
            "source": "backend_learn_module",
            "target": "backend_notes_table",
            "relation": "shares_data_with",
            "confidence": "EXTRACTED",
            "confidence_score": 1.0,
            "source_file": "BACKEND.md",
            "source_location": "30",
            "weight": 1.0
        },
        {
            "source": "backend_quiz_module",
            "target": "backend_mcq_questions_table",
            "relation": "shares_data_with",
            "confidence": "EXTRACTED",
            "confidence_score": 1.0,
            "source_file": "BACKEND.md",
            "source_location": "31",
            "weight": 1.0
        },
        {
            "source": "backend_quiz_module",
            "target": "backend_mcq_attempts_table",
            "relation": "shares_data_with",
            "confidence": "EXTRACTED",
            "confidence_score": 1.0,
            "source_file": "BACKEND.md",
            "source_location": "31",
            "weight": 1.0
        },
        {
            "source": "backend_quiz_module",
            "target": "backend_daily_challenges_table",
            "relation": "shares_data_with",
            "confidence": "EXTRACTED",
            "confidence_score": 1.0,
            "source_file": "BACKEND.md",
            "source_location": "31",
            "weight": 1.0
        },
        {
            "source": "backend_gamification_module",
            "target": "backend_attendance_table",
            "relation": "shares_data_with",
            "confidence": "EXTRACTED",
            "confidence_score": 1.0,
            "source_file": "BACKEND.md",
            "source_location": "32",
            "weight": 1.0
        },
        {
            "source": "backend_gamification_module",
            "target": "backend_achievements_table",
            "relation": "shares_data_with",
            "confidence": "EXTRACTED",
            "confidence_score": 1.0,
            "source_file": "BACKEND.md",
            "source_location": "32",
            "weight": 1.0
        },
        {
            "source": "backend_gamification_module",
            "target": "backend_profiles_table",
            "relation": "shares_data_with",
            "confidence": "EXTRACTED",
            "confidence_score": 1.0,
            "source_file": "BACKEND.md",
            "source_location": "32",
            "weight": 1.0
        },
        {
            "source": "backend_certificates_module",
            "target": "backend_certificates_table",
            "relation": "shares_data_with",
            "confidence": "EXTRACTED",
            "confidence_score": 1.0,
            "source_file": "BACKEND.md",
            "source_location": "33",
            "weight": 1.0
        },
        {
            "source": "backend_notifications_module",
            "target": "backend_email_logs_table",
            "relation": "shares_data_with",
            "confidence": "EXTRACTED",
            "confidence_score": 1.0,
            "source_file": "BACKEND.md",
            "source_location": "35",
            "weight": 1.0
        },
        {
            "source": "backend_auth_module",
            "target": "backend_authservice",
            "relation": "conceptually_related_to",
            "confidence": "EXTRACTED",
            "confidence_score": 1.0,
            "source_file": "BACKEND.md",
            "source_location": "537",
            "weight": 1.0
        },
        {
            "source": "backend_users_module",
            "target": "backend_userservice",
            "relation": "conceptually_related_to",
            "confidence": "EXTRACTED",
            "confidence_score": 1.0,
            "source_file": "BACKEND.md",
            "source_location": "538",
            "weight": 1.0
        },
        {
            "source": "backend_courses_module",
            "target": "backend_courseservice",
            "relation": "conceptually_related_to",
            "confidence": "EXTRACTED",
            "confidence_score": 1.0,
            "source_file": "BACKEND.md",
            "source_location": "539",
            "weight": 1.0
        },
        {
            "source": "backend_import_module",
            "target": "backend_importservice",
            "relation": "conceptually_related_to",
            "confidence": "EXTRACTED",
            "confidence_score": 1.0,
            "source_file": "BACKEND.md",
            "source_location": "540",
            "weight": 1.0
        },
        {
            "source": "backend_learn_module",
            "target": "backend_progressservice",
            "relation": "conceptually_related_to",
            "confidence": "EXTRACTED",
            "confidence_score": 1.0,
            "source_file": "BACKEND.md",
            "source_location": "542",
            "weight": 1.0
        },
        {
            "source": "backend_quiz_module",
            "target": "backend_quizservice",
            "relation": "conceptually_related_to",
            "confidence": "EXTRACTED",
            "confidence_score": 1.0,
            "source_file": "BACKEND.md",
            "source_location": "544",
            "weight": 1.0
        },
        {
            "source": "backend_gamification_module",
            "target": "backend_gamificationservice",
            "relation": "conceptually_related_to",
            "confidence": "EXTRACTED",
            "confidence_score": 1.0,
            "source_file": "BACKEND.md",
            "source_location": "546",
            "weight": 1.0
        },
        {
            "source": "backend_certificates_module",
            "target": "backend_certificateservice",
            "relation": "conceptually_related_to",
            "confidence": "EXTRACTED",
            "confidence_score": 1.0,
            "source_file": "BACKEND.md",
            "source_location": "547",
            "weight": 1.0
        },
        {
            "source": "backend_tutor_module",
            "target": "backend_tutorservice",
            "relation": "conceptually_related_to",
            "confidence": "EXTRACTED",
            "confidence_score": 1.0,
            "source_file": "BACKEND.md",
            "source_location": "548",
            "weight": 1.0
        },
        {
            "source": "backend_notifications_module",
            "target": "backend_notificationservice",
            "relation": "conceptually_related_to",
            "confidence": "EXTRACTED",
            "confidence_score": 1.0,
            "source_file": "BACKEND.md",
            "source_location": "549",
            "weight": 1.0
        },
        {
            "source": "backend_admin_module",
            "target": "backend_adminservice",
            "relation": "conceptually_related_to",
            "confidence": "EXTRACTED",
            "confidence_score": 1.0,
            "source_file": "BACKEND.md",
            "source_location": "550",
            "weight": 1.0
        },
        {
            "source": "backend_platform_module",
            "target": "backend_ratelimitservice",
            "relation": "conceptually_related_to",
            "confidence": "EXTRACTED",
            "confidence_score": 1.0,
            "source_file": "BACKEND.md",
            "source_location": "554",
            "weight": 1.0
        },
        {
            "source": "backend_platform_module",
            "target": "backend_redis_strategy",
            "relation": "conceptually_related_to",
            "confidence": "EXTRACTED",
            "confidence_score": 1.0,
            "source_file": "BACKEND.md",
            "source_location": "595",
            "weight": 1.0
        },
        {
            "source": "backend_authservice",
            "target": "backend_jwt_rs256",
            "relation": "conceptually_related_to",
            "confidence": "EXTRACTED",
            "confidence_score": 1.0,
            "source_file": "BACKEND.md",
            "source_location": "494",
            "weight": 1.0
        },
        {
            "source": "backend_progressservice",
            "target": "backend_outbox_pattern",
            "relation": "conceptually_related_to",
            "confidence": "EXTRACTED",
            "confidence_score": 1.0,
            "source_file": "BACKEND.md",
            "source_location": "542",
            "weight": 1.0
        },
        {
            "source": "backend_zverts_backend",
            "target": "product_zverts",
            "relation": "references",
            "confidence": "EXTRACTED",
            "confidence_score": 1.0,
            "source_file": "BACKEND.md",
            "source_location": "3",
            "weight": 1.0
        },
        {
            "source": "backend_zverts_backend",
            "target": "frontend_zverts_frontend",
            "relation": "conceptually_related_to",
            "confidence": "INFERRED",
            "confidence_score": 0.85,
            "source_file": "BACKEND.md",
            "source_location": "3",
            "weight": 1.0
        },
        {
            "source": "backend_outbox_pattern",
            "target": "backend_sse_hub",
            "relation": "conceptually_related_to",
            "confidence": "INFERRED",
            "confidence_score": 0.85,
            "source_file": "BACKEND.md",
            "source_location": "44",
            "weight": 1.0
        }
    ],
    "hyperedges": [
        {
            "id": "backend_service_layer",
            "label": "Backend Service Layer: All Go Service Interfaces",
            "nodes": [
                "backend_authservice",
                "backend_userservice",
                "backend_courseservice",
                "backend_importservice",
                "backend_progressservice",
                "backend_quizservice",
                "backend_gamificationservice",
                "backend_certificateservice",
                "backend_tutorservice",
                "backend_notificationservice",
                "backend_adminservice"
            ],
            "relation": "implement",
            "confidence": "EXTRACTED",
            "confidence_score": 1.0,
            "source_file": "BACKEND.md"
        }
    ]
}
